csic_driver_base/__init__.py
csic_driver_base/__version__.py
csic_driver_base/drv_base_pwr.py
csic_driver_base/drv_base_status.py
csic_driver_base-0.0.1.dist-info/LICENSE.txt
csic_driver_base-0.0.1.dist-info/METADATA
csic_driver_base-0.0.1.dist-info/WHEEL
csic_driver_base-0.0.1.dist-info/top_level.txt
csic_driver_base-0.0.1.dist-info/RECORD
